certbot_pkcs12.py
certbot_pkcs12-0.3.1.dist-info/METADATA
certbot_pkcs12-0.3.1.dist-info/WHEEL
certbot_pkcs12-0.3.1.dist-info/entry_points.txt
certbot_pkcs12-0.3.1.dist-info/top_level.txt
certbot_pkcs12-0.3.1.dist-info/RECORD
