Metadata-Version: 2.4
Name: certbot-pkcs12
Version: 0.3.1
Summary: PKCS#12 installer plugin for Certbot and Let's Encrypt
Author-email: Leo Singer <leo.singer@ligo.org>
License-Expression: Apache-2.0
Project-URL: source, https://github.com/nasa-gcn/certbot-pkcs12
Classifier: Development Status :: 3 - Alpha
Classifier: Environment :: Plugins
Classifier: Intended Audience :: Information Technology
Classifier: Intended Audience :: System Administrators
Classifier: Topic :: Internet :: WWW/HTTP
Classifier: Topic :: Security :: Cryptography
Requires-Python: >=3.8
Requires-Dist: certbot>=1.19.0
Requires-Dist: cryptography>=42.0.8
